bangladesh/__init__.py
bangladesh/data.py
bangladesh/main.py
bangladesh/data/districts.json
bangladesh/data/divisions.json
bangladesh/data/postcodes.json
bangladesh/data/upazila-district-division.json
bangladesh/data/upazilas.json
bangladesh/models/__init__.py
bangladesh/models/district.py
bangladesh/models/districts_geo.py
bangladesh/models/division.py
bangladesh/models/postcode.py
bangladesh/models/udd.py
bangladesh/models/upazila.py
bangladesh-0.0.10.dist-info/LICENSE
bangladesh-0.0.10.dist-info/METADATA
bangladesh-0.0.10.dist-info/WHEEL
bangladesh-0.0.10.dist-info/top_level.txt
bangladesh-0.0.10.dist-info/RECORD
