Metadata-Version: 2.1
Name: bangladesh
Version: 0.0.10
Summary: A python package For Bangladesh information (District, Division, Thana, post code and etc)
Home-page: https://github.com/Druvo/Bangladesh
Author: zhdruvo (Zahid Hasan)
Author-email: <zhdruvo@gmail.com>
License: MIT License
Download-URL: https://github.com/Druvo/Bangladesh/releases/
Project-URL: Documentation, https://github.com/Druvo/Bangladesh/blob/main/README.md
Project-URL: Source, https://github.com/Druvo/Bangladesh
Project-URL: Tracker, https://github.com/Druvo/Bangladesh/issues
Keywords: bangladesh,district,division,thana,upazilas
Platform: UNKNOWN
Classifier: Development Status :: 4 - Beta
Classifier: Intended Audience :: Developers
Classifier: Programming Language :: Python
Classifier: Programming Language :: Python :: 2.7
Classifier: Programming Language :: Python :: 3
Classifier: Programming Language :: Python :: 3.4
Classifier: Programming Language :: Python :: 3.5
Classifier: Programming Language :: Python :: 3.6
Classifier: Programming Language :: Python :: 3.7
Classifier: Programming Language :: Python :: 3.8
Classifier: Operating System :: OS Independent
Classifier: License :: OSI Approved :: MIT License
Classifier: Topic :: Software Development
Classifier: Topic :: Terminals
Classifier: Topic :: Utilities
Classifier: Topic :: Communications
Classifier: Topic :: Education
Classifier: Topic :: Sociology :: Genealogy
Classifier: Topic :: System :: Archiving :: Packaging
